{"authorDailyContributionsMap":{"zuohui48":[{"date":"2023-01-19","commitResults":[{"hash":"448e8f1e704bf2b6fdf76ce32612416d987aa4a4","messageTitle":"Level 1. Greet, Echo, Exit","messageBody":"","tags":["Level-1"],"fileTypesAndContributionMap":{"java":{"insertions":15,"deletions":1}}},{"hash":"4990edcb59206ef008e5a50723842d3f876f67cc","messageTitle":"Level 2. Add, List","messageBody":"","tags":["Level-2"],"fileTypesAndContributionMap":{"java":{"insertions":23,"deletions":1}}},{"hash":"55b36edc674576494dcb6c10c701909941e7b586","messageTitle":"Level 3. Mark as Done","messageBody":"","tags":["Level-3"],"fileTypesAndContributionMap":{"java":{"insertions":33,"deletions":8}}},{"hash":"33ecb546f48b14f85bf0d20822ffdb4d42aa9e68","messageTitle":"Level 4. ToDos, Events, Deadlines","messageBody":"","tags":["Level-4"],"fileTypesAndContributionMap":{"java":{"insertions":62,"deletions":2}}}]},{"date":"2023-01-20","commitResults":[{"hash":"626ffc6f90708ddfa971ec78d7b9b26f31c6a86a","messageTitle":"Handle errors","messageBody":"","tags":["Level-5"],"fileTypesAndContributionMap":{"java":{"insertions":50,"deletions":16}}},{"hash":"b16fc63ae71cc293f2bfe85afcca0d12f57e85e6","messageTitle":"enable deletion of tasks","messageBody":"","fileTypesAndContributionMap":{"java":{"insertions":6,"deletions":1}}},{"hash":"96ad5de5b5d4142a25e3bf35e38f2dab846e6b19","messageTitle":"enable deletion of tasks","messageBody":"","tags":["Level-6"],"fileTypesAndContributionMap":{"txt":{"insertions":8,"deletions":0}}}]},{"date":"2023-01-28","commitResults":[{"hash":"c06097e1467e8b890da2064652d509f6b75a417c","messageTitle":"Save and load data from Duke.txt","messageBody":"","tags":["Level-7"],"fileTypesAndContributionMap":{"java":{"insertions":83,"deletions":10}}},{"hash":"ec5113772465e04dea762858077e5c965b3382af","messageTitle":"Add date and time","messageBody":"","tags":["Level-8"],"fileTypesAndContributionMap":{"java":{"insertions":72,"deletions":19}}},{"hash":"3d3e25a783a063c22ca4a25bfbc4bdd4670c63bf","messageTitle":"Fix loading data","messageBody":"","fileTypesAndContributionMap":{"java":{"insertions":38,"deletions":8}}},{"hash":"ed5bc8406e4cfd66233ba50c719f179293063727","messageTitle":"Implement more OOP","messageBody":"","tags":["A-MoreOOP"],"fileTypesAndContributionMap":{"java":{"insertions":362,"deletions":218}}}]},{"date":"2023-01-30","commitResults":[{"hash":"ac2a400820071a11eae7bdea211f6056587d142c","messageTitle":"add packages","messageBody":"","tags":["A-Packages"],"fileTypesAndContributionMap":{"java":{"insertions":16,"deletions":442}}},{"hash":"b32d74249f0c3511d7013ff2c3a075a093ba9329","messageTitle":"Use Gradle","messageBody":"","tags":["A-Gradle"],"fileTypesAndContributionMap":{"java":{"insertions":5,"deletions":0}}},{"hash":"cf50cb391e4fcc70017a9aafddbcda088cd8c3d1","messageTitle":"Add folders","messageBody":"","fileTypesAndContributionMap":{"java":{"insertions":464,"deletions":0}}}]},{"date":"2023-01-31","commitResults":[{"hash":"73ec48ed9d33c20cdaacb8e04808b07437e43165","messageTitle":"add JUnit tests for Task and Deadline","messageBody":"","tags":["A-JUnit"],"fileTypesAndContributionMap":{"txt":{"insertions":5,"deletions":0},"java":{"insertions":10,"deletions":0}}},{"hash":"9c739e18c1afd68b5765c1d27bd7881102eb20f3","messageTitle":"Add JUnit tests for Task and Deadline","messageBody":"","fileTypesAndContributionMap":{"java":{"insertions":47,"deletions":2}}}]}]},"authorFileTypeContributionMap":{"zuohui48":{"java":568,"md":0,"fxml":0,"sh":0,"bat":0,"gradle":0,"txt":13}},"authorContributionVariance":{"zuohui48":70045.38},"authorDisplayNameMap":{"zuohui48":"CS2103-F11-2 CHEN.. HUI"}}
