{"authorDailyContributionsMap":{"evanpy":[{"date":"2023-01-17","commitResults":[{"hash":"48c84511224664c3a339f8491458d87292070beb","messageTitle":"Added echo functionality","messageBody":"","tags":["Level-1"],"fileTypesAndContributionMap":{"java":{"insertions":47,"deletions":8}}},{"hash":"ca593633974e57fd30dc4b5b0d48a40aee2280f7","messageTitle":"Added task adding and listing functionality","messageBody":"","tags":["Level-2"],"fileTypesAndContributionMap":{"java":{"insertions":34,"deletions":8}}},{"hash":"f341f5d197533fdda4b61c8c37c2b8157b7ea0c6","messageTitle":"Added Task class that can be marked/unmarked","messageBody":"","tags":["Level-3"],"fileTypesAndContributionMap":{"java":{"insertions":84,"deletions":5}}}]},{"date":"2023-01-19","commitResults":[{"hash":"1fc6cd2fad7f10b0558e1a3abed2be5b898aa6b7","messageTitle":"Added Task types","messageBody":"","tags":["Level-4"],"fileTypesAndContributionMap":{"java":{"insertions":95,"deletions":15}}},{"hash":"089e789e0a4d6ed938afe0f29b80757f5c3433ab","messageTitle":"Modified testing files for automatic testing for bot","messageBody":"","tags":["A-TextUiTesting"],"fileTypesAndContributionMap":{"txt":{"insertions":5,"deletions":0}}},{"hash":"a7645213aba366ef9179fd4827ebb4361bf709cf","messageTitle":"Modified test files","messageBody":"","fileTypesAndContributionMap":{"txt":{"insertions":2,"deletions":0}}},{"hash":"c00c3796b8ef21643b1e9782d08dd2455e08b4b7","messageTitle":"Added exception handling for unknown input and missing task description","messageBody":"","tags":["Level-5","A-Exceptions"],"fileTypesAndContributionMap":{"java":{"insertions":43,"deletions":14}}},{"hash":"8c00ad8ea7481405081a88c63aa942d4bf8d2c76","messageTitle":"Modified test files","messageBody":"","fileTypesAndContributionMap":{"txt":{"insertions":1,"deletions":0}}},{"hash":"f38bd291736d305bf23f76e2dccabf66818873dc","messageTitle":"Added constructor documentation","messageBody":"","fileTypesAndContributionMap":{"java":{"insertions":5,"deletions":0}}},{"hash":"65b648a6883af57e56d9df32502fc70fb8e3565f","messageTitle":"Added support for deleting tasks","messageBody":"","tags":["Level-6","Delete"],"fileTypesAndContributionMap":{"java":{"insertions":24,"deletions":9}}}]},{"date":"2023-01-24","commitResults":[{"hash":"5455b98128fc562a913126cce498fb57e064a646","messageTitle":"Edit Javadoc of mark and unmark methods","messageBody":"","fileTypesAndContributionMap":{"java":{"insertions":2,"deletions":2}}},{"hash":"7548227d7164a27d0c7f23ff3eb9487f6ff2c01f","messageTitle":"Refactor code and modify code to comply with coding standard","messageBody":"","fileTypesAndContributionMap":{"java":{"insertions":69,"deletions":56}}}]}]},"authorFileTypeContributionMap":{"evanpy":{"java":292,"md":0,"fxml":0,"sh":0,"bat":0,"gradle":0,"txt":8}},"authorContributionVariance":{"evanpy":6114.5},"authorDisplayNameMap":{"evanpy":"LEE .. JUN"}}
